redisz/__init__.py
redisz/utils.py
test/__init__.py
test/pubsub_test.py
unit_test/__init__.py
unit_test/ext_test.py
unit_test/global_test.py
unit_test/hash_test.py
unit_test/list_test.py
unit_test/lock_test.py
unit_test/set_test.py
unit_test/str_test.py
unit_test/zset_test.py
redisz-0.7.dist-info/LICENSE
redisz-0.7.dist-info/METADATA
redisz-0.7.dist-info/WHEEL
redisz-0.7.dist-info/top_level.txt
redisz-0.7.dist-info/RECORD
