Metadata-Version: 2.1
Name: redisz
Version: 0.7
Summary: redis toolset
Home-page: https://github.com/taozh1982/redisz
Author: Zhang Tao
Author-email: taozh1982@gmail.com
Project-URL: Bug Tracker, https://github.com/taozh1982/redisz/issues
Classifier: Programming Language :: Python :: 3
Classifier: License :: OSI Approved :: MIT License
Classifier: Operating System :: OS Independent
Requires-Python: >=3.6
License-File: LICENSE
Requires-Dist: redis >=4.2.0
